{
  "education": [
    {
      "degree": "Doctor of Philosophy (PhD) in Business Analytics",
      "institution": "University of Lausanne (UNIL)",
      "location": "Lausanne, Switzerland",
      "dates": "May 2019 - February 2023",
      "dissertation": "High-performance computing approaches to solve large-scale dynamic models in economics and finance",
      "focus_areas": [
        "Dynamic programming",
        "Compilers",
        "C++",
        "Combinatorics",
        "GPGPU",
        "High Performance Computing (HPC)"
      ]
    },
    {
      "degree": "Computational Mathematics and System Programming",
      "institution": "Lomonosov Moscow State University (MSU)",
      "location": "Moscow, Russia",
      "dates": "2003 - 2008",
      "department": "Department of Computational Technologies and Modelling (Institute of Numerical Mathematics, Russian Academy of Science)"
    }
  ]
}
